emark/__init__.py
emark/_version.py
emark/backends.py
emark/conf.py
emark/message.py
emark/models.py
emark/urls.py
emark/utils.py
emark/views.py
emark/contrib/__init__.py
emark/contrib/dashboard/__init__.py
emark/contrib/dashboard/apps.py
emark/contrib/dashboard/urls.py
emark/contrib/dashboard/views.py
emark/contrib/dashboard/templates/admin/base_site.html
emark/contrib/dashboard/templates/emark/dashboard/dashboard.html
emark/contrib/dashboard/templates/emark/dashboard/preview.html
emark/locale/de/LC_MESSAGES/django.mo
emark/locale/de/LC_MESSAGES/django.po
emark/migrations/0001_initial.py
emark/migrations/0002_rename_from_address_send_from_email_and_more.py
emark/migrations/__init__.py
emark/templates/emark/base.html
emark/templates/emark/license.txt
emark/templates/emark/styles.css
emark-2.2.0.dist-info/licenses/LICENSE
emark-2.2.0.dist-info/WHEEL
emark-2.2.0.dist-info/METADATA
emark-2.2.0.dist-info/RECORD
