Metadata-Version: 2.4
Name: emark
Version: 2.2.0
Summary: Markdown template based HTML and text emails for Django.
Keywords: Markdown,Django,email,templates,HTML
Author-email: Rust Saiargaliev <fly.amureki@gmail.com>, Johannes Maron <johannes@maron.family>, Mostafa Mohamed <mostafa.anm91@gmail.com>, Jacqueline Kraus <jacquelinekraus1992@gmail.com>
Requires-Python: >=3.10
Classifier: Development Status :: 5 - Production/Stable
Classifier: Programming Language :: Python
Classifier: Environment :: Web Environment
Classifier: License :: OSI Approved :: BSD License
Classifier: Intended Audience :: Developers
Classifier: Operating System :: OS Independent
Classifier: Topic :: Communications :: Email
Classifier: Topic :: Text Processing :: Markup :: Markdown
Classifier: Topic :: Text Processing :: Markup :: HTML
Classifier: Topic :: Software Development
Classifier: Programming Language :: Python
Classifier: Programming Language :: Python :: 3
Classifier: Programming Language :: Python :: 3 :: Only
Classifier: Programming Language :: Python :: 3.10
Classifier: Programming Language :: Python :: 3.11
Classifier: Programming Language :: Python :: 3.12
Classifier: Programming Language :: Python :: 3.13
Classifier: Programming Language :: Python :: 3.14
Classifier: Framework :: Django
Classifier: Framework :: Django :: 4.2
Classifier: Framework :: Django :: 5.2
Classifier: Framework :: Django :: 6.0
License-File: LICENSE
Requires-Dist: django>=4.2
Requires-Dist: markdown
Requires-Dist: premailer
Requires-Dist: pytest ; extra == "test"
Requires-Dist: pytest-cov ; extra == "test"
Requires-Dist: pytest-django ; extra == "test"
Requires-Dist: model_bakery ; extra == "test"
Project-URL: Changelog, https://github.com/voiio/emark/releases
Project-URL: Project-URL, https://github.com/voiio/emark
Provides-Extra: test
